fastnet_decoder/__init__.py
fastnet_decoder/decode_fastnet.py
fastnet_decoder/frame_buffer.py
fastnet_decoder/logger.py
fastnet_decoder/mappings.py
fastnet_decoder/utils.py
pyfastnet-1.1.9.dist-info/licenses/LICENSE
pyfastnet-1.1.9.dist-info/METADATA
pyfastnet-1.1.9.dist-info/WHEEL
pyfastnet-1.1.9.dist-info/top_level.txt
pyfastnet-1.1.9.dist-info/RECORD
