Metadata-Version: 2.4
Name: pyfastnet
Version: 1.1.9
Summary: A Python library for decoding FastNet protocol data streams.
Home-page: https://github.com/ghotihook/pyfastnet
Author: Alex Salmon
Author-email: alex@ivila.net
Classifier: Programming Language :: Python :: 3
Classifier: License :: OSI Approved :: MIT License
Classifier: Operating System :: OS Independent
Requires-Python: >=3.7
License-File: LICENSE
Dynamic: author
Dynamic: author-email
Dynamic: classifier
Dynamic: description
Dynamic: description-content-type
Dynamic: home-page
Dynamic: license-file
Dynamic: requires-python
Dynamic: summary
